AUTHORS.rst
CONTRIBUTING.rst
HISTORY.rst
LICENSE
MANIFEST.in
requirements.txt
setup.cfg
setup.py
zappa_file_widget/__init__.py
zappa_file_widget/file_widget.py
zappa_file_widget/url_widget.py
zappa_file_widget_mediabucket.egg-info/PKG-INFO
zappa_file_widget_mediabucket.egg-info/SOURCES.txt
zappa_file_widget_mediabucket.egg-info/dependency_links.txt
zappa_file_widget_mediabucket.egg-info/not-zip-safe
zappa_file_widget_mediabucket.egg-info/requires.txt
zappa_file_widget_mediabucket.egg-info/top_level.txt