Metadata-Version: 1.1
Name: zappa-file-widget-mediabucket
Version: 0.1.6b0
Summary: Django Admin File Wiget for Zappa based admin panels, forked to allow use of a different bucket for media files
Home-page: https://github.com/rebost/zappa-file-widget
Author: Matías Pizarro
Author-email: matias@pizarro.net
License: MIT
Keywords: zappa-file-widget
Platform: UNKNOWN
Classifier: Development Status :: 3 - Alpha
Classifier: Framework :: Django
Classifier: Framework :: Django :: 1.10
Classifier: Intended Audience :: Developers
Classifier: License :: OSI Approved :: BSD License
Classifier: Natural Language :: English
Classifier: Programming Language :: Python :: 2
Classifier: Programming Language :: Python :: 2.7
Classifier: Programming Language :: Python :: 3
Classifier: Programming Language :: Python :: 3.4
Classifier: Programming Language :: Python :: 3.5
